{
    "main":"@main",
    "index":"index4.json",
    "name":"dxib/xstory测试test--ok-xcard",
    "xmsg":"dxib/xstory测试test--ok-xcard", 
    "logo":"dtns://web3:ld/image/view?filename=obj_imgopenCLb1zHyiq&img_kind=open", 
    "xtype":"dxib",
    "dxib_url":"dtns://web3:ld/file?filename=obj_filefileAPDt6r3C",
    "player":"xvideo",
    "actions_type":"json",
    "actions":
    [
        {
            "name":"@main", 
            "url":"dtns://web3:ld/file?filename=obj_filefileAm3wZ173",
            "xtype":"video",
            "ended":"@main_ended", 
            "deps":["@main_ended","@r2tips"],
            "history":true 
        },
        {
            "name":"@main_ended",
            "url":"videoTips4.json",
            "xtype":"minicard",
            "new":"",
            "history":true, 
            "deps":["@good","@good2"] 
        },
        {
            "name":"@good",
            "url":"dtns://web3:ld/file?filename=obj_filefile2cyfi6tS",
            "xtype":"video", 
            "new":"",
            "history":true 
        },
        {
            "name":"@good2",
            "url":"dtns://web3:ld/file?filename=obj_filefileFrrPPCqc",
            "xtype":"video", 
            "new":"",
            "history":true 
        },
        {
            "name":"@ftips",
            "url":"ftips.json",
            "xtype":"minicard", 
            "new":"",
            "history":true 
        },
        {
            "name":"@r2tips",
            "url":"r2tips.json",
            "xtype":"minicard", 
            "new":"",
            "history":true 
        }
    ]
}
